LICENSE
MANIFEST.in
NEWS
README
setup.cfg
setup.py
authorize/__init__.py
authorize/aim.py
authorize/arb.py
authorize/base.py
authorize/cim.py
authorize/gen_xml.py
authorize/responses.py
authorize/util.py
authorize.egg-info/PKG-INFO
authorize.egg-info/SOURCES.txt
authorize.egg-info/dependency_links.txt
authorize.egg-info/top_level.txt
authorize/tests/__init__.py
authorize/tests/schema.py
authorize/tests/test_api.py
authorize/tests/test_xml.py