Metadata-Version: 1.0
Name: authorize
Version: 0.1.0
Summary: An API to connect to authorize.net(TM) payment services.
Home-page: http://adroll.com/labs
Author: Valentino Volonghi
Author-email: valentino@adroll.com
License: MIT License
Platform: UNKNOWN
Classifier: Development Status :: 4 - Beta
Classifier: Environment :: Web Environment
Classifier: Intended Audience :: Developers
Classifier: License :: OSI Approved :: MIT License
Classifier: Natural Language :: English
Classifier: Programming Language :: Python
Classifier: Topic :: Internet
